onedevcommonmsgraph/__init__.py
onedevcommonmsgraph/email_.py
onedevcommonmsgraph/email_analyzer.py
onedevcommonmsgraph/email_reader.py
onedevcommonmsgraph/logs/.gitkeep
onedevcommonmsgraph-1.0.3.dist-info/METADATA
onedevcommonmsgraph-1.0.3.dist-info/WHEEL
onedevcommonmsgraph-1.0.3.dist-info/RECORD
